Workbook

Sheet Dashboard
A1: Dashboard financeiro doméstico
A3: Mês de análise | B3: 46235
A5: Receitas realizadas | D5: Despesas realizadas | G5: Saldo do mês | J5: Economia %
A6: =SUMIFS(Lançamentos!$I:$I,Lançamentos!$B:$B,$B$3,Lançamentos!$C:$C,"Receita") -> 17632.86 | D6: =SUMIFS(Lançamentos!$I:$I,Lançamentos!$B:$B,$B$3,Lançamentos!$C:$C,"Despesa") -> 12565.1 | G6: =B6-E6 -> 0 | J6: =IFERROR(G6/B6,0) -> 0
A10: Limite disponível | D10: Faturas em aberto | G10: Saldo de dívidas | J10: Metas — progresso médio
A11: =SUM(Cartões!$E$4:$E$53) -> 1855.15 | D11: =SUMIFS(Cartões!$H:$H,Cartões!$I:$I,"Aberta") -> 5549.77 | G11: =SUM(Dívidas!$D$4:$D$83) -> 10174.66 | J11: =IFERROR(AVERAGE(Metas!$F$4:$F$83),0) -> 0.0032142857
A16: Mês | B16: Receitas | C16: Despesas | D16: Saldo | G16: Categoria | H16: Despesas
A17: ='Planejamento Mensal'!A4 -> 46235 | B17: ='Planejamento Mensal'!C4 -> 17632.86 | C17: ='Planejamento Mensal'!E4 -> 12565.1 | D17: ='Planejamento Mensal'!G4 -> 5067.76 | G17: Moradia | H17: =SUMIFS(Lançamentos!$I:$I,Lançamentos!$B:$B,$B$3,Lançamentos!$C:$C,"Despesa",Lançamentos!$E:$E,G17) -> 3000
A18: ='Planejamento Mensal'!A5 -> 46266 | B18: ='Planejamento Mensal'!C5 -> 0 | C18: ='Planejamento Mensal'!E5 -> 0 | D18: ='Planejamento Mensal'!G5 -> 0 | G18: Alimentação | H18: =SUMIFS(Lançamentos!$I:$I,Lançamentos!$B:$B,$B$3,Lançamentos!$C:$C,"Despesa",Lançamentos!$E:$E,G18) -> 549.46
A19: ='Planejamento Mensal'!A6 -> 46296 | B19: ='Planejamento Mensal'!C6 -> 0 | C19: ='Planejamento Mensal'!E6 -> 0 | D19: ='Planejamento Mensal'!G6 -> 0 | G19: Transporte | H19: =SUMIFS(Lançamentos!$I:$I,Lançamentos!$B:$B,$B$3,Lançamentos!$C:$C,"Despesa",Lançamentos!$E:$E,G19) -> 98.37
A20: ='Planejamento Mensal'!A7 -> 46327 | B20: ='Planejamento Mensal'!C7 -> 0 | C20: ='Planejamento Mensal'!E7 -> 0 | D20: ='Planejamento Mensal'!G7 -> 0 | G20: Saúde | H20: =SUMIFS(Lançamentos!$I:$I,Lançamentos!$B:$B,$B$3,Lançamentos!$C:$C,"Despesa",Lançamentos!$E:$E,G20) -> 130
A21: ='Planejamento Mensal'!A8 -> 46357 | B21: ='Planejamento Mensal'!C8 -> 0 | C21: ='Planejamento Mensal'!E8 -> 0 | D21: ='Planejamento Mensal'!G8 -> 0 | G21: Educação | H21: =SUMIFS(Lançamentos!$I:$I,Lançamentos!$B:$B,$B$3,Lançamentos!$C:$C,"Despesa",Lançamentos!$E:$E,G21) -> 109.29
A22: ='Planejamento Mensal'!A9 -> 46388 | B22: ='Planejamento Mensal'!C9 -> 0 | C22: ='Planejamento Mensal'!E9 -> 0 | D22: ='Planejamento Mensal'!G9 -> 0 | G22: Lazer | H22: =SUMIFS(Lançamentos!$I:$I,Lançamentos!$B:$B,$B$3,Lançamentos!$C:$C,"Despesa",Lançamentos!$E:$E,G22) -> 85.92
A23: ='Planejamento Mensal'!A10 -> 46419 | B23: ='Planejamento Mensal'!C10 -> 0 | C23: ='Planejamento Mensal'!E10 -> 0 | D23: ='Planejamento Mensal'!G10 -> 0 | G23: Assinaturas | H23: =SUMIFS(Lançamentos!$I:$I,Lançamentos!$B:$B,$B$3,Lançamentos!$C:$C,"Despesa",Lançamentos!$E:$E,G23) -> 72.89
A24: ='Planejamento Mensal'!A11 -> 46447 | B24: ='Planejamento Mensal'!C11 -> 0 | C24: ='Planejamento Mensal'!E11 -> 0 | D24: ='Planejamento Mensal'!G11 -> 0 | G24: Impostos | H24: =SUMIFS(Lançamentos!$I:$I,Lançamentos!$B:$B,$B$3,Lançamentos!$C:$C,"Despesa",Lançamentos!$E:$E,G24) -> 0
A25: ='Planejamento Mensal'!A12 -> 46478 | B25: ='Planejamento Mensal'!C12 -> 0 | C25: ='Planejamento Mensal'!E12 -> 0 | D25: ='Planejamento Mensal'!G12 -> 0 | G25: Compras | H25: =SUMIFS(Lançamentos!$I:$I,Lançamentos!$B:$B,$B$3,Lançamentos!$C:$C,"Despesa",Lançamentos!$E:$E,G25) -> 304.09
A26: ='Planejamento Mensal'!A13 -> 46508 | B26: ='Planejamento Mensal'!C13 -> 0 | C26: ='Planejamento Mensal'!E13 -> 0 | D26: ='Planejamento Mensal'!G13 -> 0 | G26: Investimentos | H26: =SUMIFS(Lançamentos!$I:$I,Lançamentos!$B:$B,$B$3,Lançamentos!$C:$C,"Despesa",Lançamentos!$E:$E,G26) -> 4683.05
A27: ='Planejamento Mensal'!A14 -> 46539 | B27: ='Planejamento Mensal'!C14 -> 0 | C27: ='Planejamento Mensal'!E14 -> 0 | D27: ='Planejamento Mensal'!G14 -> 0 | G27: Pensão | H27: =SUMIFS(Lançamentos!$I:$I,Lançamentos!$B:$B,$B$3,Lançamentos!$C:$C,"Despesa",Lançamentos!$E:$E,G27) -> 1134.7
A28: ='Planejamento Mensal'!A15 -> 46569 | B28: ='Planejamento Mensal'!C15 -> 0 | C28: ='Planejamento Mensal'!E15 -> 0 | D28: ='Planejamento Mensal'!G15 -> 0
G31: Indicadores
G32: Economia | H32: =IFERROR(G6/B6,0) -> 0 | I32: Referência: maior é melhor para poupança
G33: Comprometimento da renda | H33: =IFERROR(E6/B6,0) -> 0 | I33: Referência: acompanhar tendência
G34: Limite de cartão utilizado | H34: =IFERROR(SUM(Cartões!$D$4:$D$53)/SUM(Cartões!$C$4:$C$53),0) -> 0.9264452 | I34: Referência: acompanhar utilização

Sheet Lançamentos
A1: Lançamentos — receitas e despesas
A3: Data | B3: Mês | C3: Tipo | D3: Descrição | E3: Categoria | F3: Forma | G3: Conta/Cartão | H3: Previsto | I3: Realizado | J3: Status | K3: Observação | L3: ID
A4: 46240 | B4: =TEXT(A4,"mmm/aaaa") -> ago/2026 | C4: Despesa | D4: Aluguel | E4: Moradia | F4: Transferência | G4: Sicoob | H4: 1500 | I4: 1500 | J4: Pago | L4: 1
A5: 46262 | B5: =IF(A5="","",TEXT(A5,"mmm/aaaa")) -> ago/2026 | C5: Receita | D5: Salário (Gdl) | E5: Renda fixa | F5: Transferência | G5: Itaú | H5: 1200 | I5: 1571 | J5: Realizado | L5: 2
A6: 46262 | B6: =IF(A6="","",TEXT(A6,"mmm/aaaa")) -> ago/2026 | C6: Receita | D6: Salário de férias (Gdl) | E6: Renda variável | F6: Transferência | G6: Itaú | H6: 2917.75 | I6: 2917.75 | J6: Realizado | L6: 3
A7: 46248 | B7: =IF(A7="","",TEXT(A7,"mmm/aaaa")) -> ago/2026 | C7: Receita | D7: Adiantamento (Gdl) | E7: Renda fixa | F7: Transferência | G7: Itaú | H7: 892.95 | I7: 892.95 | J7: Realizado | L7: 4
A8: 46265 | B8: =IF(A8="","",TEXT(A8,"mmm/aaaa")) -> ago/2026 | C8: Receita | D8: Salário (Grupo soluções) | E8: Renda fixa | F8: Transferência | G8: Itaú | H8: 405.25 | I8: 405.25 | J8: Realizado | L8: 5
A9: 46249 | B9: =IF(A9="","",TEXT(A9,"mmm/aaaa")) -> ago/2026 | C9: Receita | D9: Adiantamento (Grupo soluções) | E9: Renda fixa | F9: Transferência | G9: Itaú | H9: 405.25 | I9: 405.25 | J9: Realizado | L9: 6
A10: 46244 | B10: =IF(A10="","",TEXT(A10,"mmm/aaaa")) -> ago/2026 | C10: Receita | D10: Pró-labore (Grupo soluções) | E10: Renda fixa | F10: Transferência | G10: Sicoob | H10: 3000 | I10: 3000 | J10: Realizado | L10: 7
A11: 46254 | B11: =IF(A11="","",TEXT(A11,"mmm/aaaa")) -> ago/2026 | C11: Receita | D11: Pró-labore (Grupo soluções) | E11: Renda fixa | F11: Transferência | G11: Sicoob | H11: 3000 | I11: 3000 | J11: Realizado | L11: 8
A12: 46246 | B12: =IF(A12="","",TEXT(A12,"mmm/aaaa")) -> ago/2026 | C12: Despesa | D12: Aluguel | E12: Moradia | F12: Transferência | G12: Sicoob | H12: 1500 | I12: 1500 | J12: Pago | L12: 9
A13: 46244 | B13: =IF(A13="","",TEXT(A13,"mmm/aaaa")) -> ago/2026 | C13: Despesa | D13: Pensão | E13: Pensão | F13: PIX | G13: Sicoob | H13: 1134.7 | I13: 1134.7 | J13: Pago | L13: 10
A14: 46254 | B14: =IF(A14="","",TEXT(A14,"mmm/aaaa")) -> ago/2026 | C14: Despesa | D14: Parcela casa (5 de 23) | E14: Investimentos | F14: PIX | G14: Sicoob | H14: 3000 | I14: 3000 | J14: Pago | L14: 11
A15: 46237 | B15: =IF(A15="","",TEXT(A15,"mmm/aaaa")) -> ago/2026 | C15: Despesa | D15: Restaurante | E15: Restaurante | F15: Débito | G15: Sicoob | H15: 90.82 | I15: 90.82 | J15: Pago
A16: 46237 | B16: =IF(A16="","",TEXT(A16,"mmm/aaaa")) -> ago/2026 | C16: Despesa | D16: Bolo de niver | E16: Compras | F16: PIX | G16: Sicoob | H16: 70 | I16: 70 | J16: Pago
A17: 46237 | B17: =IF(A17="","",TEXT(A17,"mmm/aaaa")) -> ago/2026 | C17: Despesa | D17: Açai | E17: Restaurante | F17: Débito | G17: Sicoob | H17: 52 | I17: 52 | J17: Pago
A18: 46237 | B18: =IF(A18="","",TEXT(A18,"mmm/aaaa")) -> ago/2026 | C18: Despesa | D18: Uniasselvi | E18: Educação | F18: Boleto | G18: Sicoob | H18: 54.11 | I18: 54.11 | J18: Pago
A19: 46237 | B19: =IF(A19="","",TEXT(A19,"mmm/aaaa")) -> ago/2026 | C19: Receita | D19: Trimestral (Grupo soluções) | E19: Renda variável | F19: Transferência | G19: Sicoob | H19: 1000 | I19: 1000 | J19: Pago
A20: 46238 | B20: =IF(A20="","",TEXT(A20,"mmm/aaaa")) -> ago/2026 | C20: Despesa | D20: Padaria | E20: Padaria | F20: Débito | G20: Sicoob | H20: 10.09 | I20: 10.09 | J20: Pago
A21: 46240 | B21: =IF(A21="","",TEXT(A21,"mmm/aaaa")) -> ago/2026 | C21: Despesa | D21: IPVA moto | E21: Transporte | F21: PIX | G21: Sicoob | H21: 68.84 | I21: 68.84 | J21: Pago
A22: 46240 | B22: =IF(A22="","",TEXT(A22,"mmm/aaaa")) -> ago/2026 | C22: Receita | D22: Trimestral (Grupo soluções) | E22: Renda variável | F22: Transferência | G22: Sicoob | H22: 1000 | I22: 1000 | J22: Pago
A23: 46240 | B23: =IF(A23="","",TEXT(A23,"mmm/aaaa")) -> ago/2026 | C23: Receita | D23: Almoço | E23: Almoço | F23: PIX | G23: Sicoob | H23: 24 | I23: 24 | J23: Pago
A24: 46240 | B24: =IF(A24="","",TEXT(A24,"mmm/aaaa")) -> ago/2026 | C24: Despesa | D24: Celular Vivo (Ju) | E24: Assinaturas | F24: PIX | G24: Sicoob | H24: 72.89 | I24: 72.89 | J24: Pago
A25: 46241 | B25: =IF(A25="","",TEXT(A25,"mmm/aaaa")) -> ago/2026 | C25: Despesa | D25: Granel natural | E25: Compras | F25: Débito | G25: Sicoob | H25: 48.66 | I25: 48.66 | J25: Pago
A26: 46241 | B26: =IF(A26="","",TEXT(A26,"mmm/aaaa")) -> ago/2026 | C26: Despesa | D26: Da roça hortifruti | E26: Alimentação | F26: Débito | G26: Sicoob | H26: 32.88 | I26: 32.88 | J26: Pago
... A57: 46254 | B57: =IF(A57="","",TEXT(A57,"mmm/aaaa")) -> ago/2026 | C57: Despesa | D57: Devolução dízimo | E57: Devolução Dízimo | F57: PIX | G57: Sicoob | H57: 300 | I57: 300 | J57: Pago
B58: =IF(A58="","",TEXT(A58,"mmm/aaaa"))
B59: =IF(A59="","",TEXT(A59,"mmm/aaaa"))
B60: =IF(A60="","",TEXT(A60,"mmm/aaaa"))
B61: =IF(A61="","",TEXT(A61,"mmm/aaaa"))
B62: =IF(A62="","",TEXT(A62,"mmm/aaaa"))
B63: =IF(A63="","",TEXT(A63,"mmm/aaaa"))
B64: =IF(A64="","",TEXT(A64,"mmm/aaaa"))
B65: =IF(A65="","",TEXT(A65,"mmm/aaaa"))
B66: =IF(A66="","",TEXT(A66,"mmm/aaaa"))
B67: =IF(A67="","",TEXT(A67,"mmm/aaaa"))
B68: =IF(A68="","",TEXT(A68,"mmm/aaaa"))
B69: =IF(A69="","",TEXT(A69,"mmm/aaaa"))
... B202: =IF(A202="","",TEXT(A202,"mmm/aaaa"))

Sheet Contas Fixas
A1: Contas fixas e vencimentos
A3: Conta | B3: Categoria | C3: Vencimento | D3: Valor Previsto | E3: Valor Realizado | F3: Forma | G3: Recorrente? | H3: Status | I3: Mês inicial | J3: Observação
A4: Aluguel | B4: Moradia | C4: 12 | D4: 1500 | E4: 1500 | F4: PIX | G4: Sim | H4: Pago | I4: 46246
A5: Internet Claro | B5: Assinaturas | C5: 5 | D5: 130 | E5: 130 | F5: PIX | G5: Sim | H5: Pago | I5: 46239
A6: Energia | B6: Moradia | C6: 14 | D6: 340 | E6: 303.36 | F6: Boleto | G6: Sim | H6: Pago | I6: 46248
A7: Água | B7: Moradia | C7: 7 | D7: 80 | E7: 76.19 | F7: Boleto | G7: Sim | H7: Pago | I7: 46241
A8: Celular Vivo (Ju) | B8: Assinaturas | C8: 17 | D8: 72.96 | E8: 72.96 | F8: Boleto | G8: Sim | H8: Pago | I8: 46251
A9: Celular Vivo (Fe) | B9: Assinaturas | C9: 17 | D9: 69 | E9: 69 | F9: Boleto | G9: Sim | H9: Pago | I9: 46251
A10: Academia (Ju) | B10: Saúde | C10: 22 | D10: 167 | E10: 167 | F10: Cartão de crédito | G10: Sim | H10: Pago | I10: 46256
A11: Academia (Fe) | B11: Saúde | C11: 22 | D11: 167 | E11: 167 | F11: Cartão de crédito | G11: Sim | H11: Pago | I11: 46256
A12: Pensão | B12: Pensão | C12: 10 | D12: 1134.7 | E12: 1134.7 | F12: PIX | G12: Sim | H12: Pago | I12: 46244

Sheet Cartões
A1: Controle de cartões e limite disponível
A3: Cartão | B3: Banco | C3: Limite Total | D3: Limite Utilizado | E3: Limite Disponível | F3: Dia Fechamento | G3: Dia Vencimento | H3: Fatura Atual | I3: Status | J3: Observação
A4: Cartão Sicoob | B4: Sicoob | C4: 23593 | D4: 21737.85 | E4: =IF(C4="","",C4-D4) -> 1855.15 | F4: 12 | G4: 22 | H4: 3921.44 | I4: Aberta
A5: Cartão Banco do Brasil | B5: Banco do Brasil | C5: 1628.33 | D5: 1628.33 | E5: =IF(C5="","",C5-D5) -> 0 | F5: 10 | G5: 13 | H5: 1628.33 | I5: Aberta
A6: Cartão celebre | B6: Celebre | E6: =IF(C6="","",C6-D6)
E7: =IF(C7="","",C7-D7)
E8: =IF(C8="","",C8-D8)
E9: =IF(C9="","",C9-D9)
E10: =IF(C10="","",C10-D10)
E11: =IF(C11="","",C11-D11)
E12: =IF(C12="","",C12-D12)
E13: =IF(C13="","",C13-D13)
E14: =IF(C14="","",C14-D14)
E15: =IF(C15="","",C15-D15)
E16: =IF(C16="","",C16-D16)
E17: =IF(C17="","",C17-D17)
E18: =IF(C18="","",C18-D18)
... E53: =IF(C53="","",C53-D53)

Sheet Compras Parceladas
A1: Compras parceladas
A3: Compra | B3: Cartão | C3: Data | D3: Valor Total | E3: Nº Parcelas | F3: Parcela Atual | G3: Valor Parcela | H3: Parcelas Pagas | I3: Parcelas Restantes | J3: Saldo | K3: Próx. Vencimento | L3: Observação
A4: Escola dain | B4: Cartão Sicoob | C4: 46054 | D4: 450 | E4: 9 | F4: 8 | G4: =IFERROR(D4/E4,"") -> 50 | H4: 8 | I4: =IF(E4="","",MAX(E4-H4,0)) -> 1 | J4: =IF(G4="","",G4*I4) -> 50 | K4: 46317
A5: Sistema posi | B5: Cartão Sicoob | C5: 46054 | D5: 1209.96 | E5: 9 | F5: 8 | G5: =IFERROR(D5/E5,"") -> 134.44 | H5: 8 | I5: =IF(E5="","",MAX(E5-H5,0)) -> 1 | J5: =IF(G5="","",G5*I5) -> 134.44 | K5: 46317
A6: Celular Iphone | B6: Cartão Sicoob | C6: 46107 | D6: 5199 | E6: 10 | F6: 6 | G6: =IFERROR(D6/E6,"") -> 519.9 | H6: 6 | I6: =IF(E6="","",MAX(E6-H6,0)) -> 4 | J6: =IF(G6="","",G6*I6) -> 2079.6 | K6: 46317
A7: Shoppe (quarto) | B7: Cartão Sicoob | C7: 46189 | D7: 498.9 | E7: 5 | F7: 3 | G7: =IFERROR(D7/E7,"") -> 99.78 | H7: 3 | I7: =IF(E7="","",MAX(E7-H7,0)) -> 2 | J7: =IF(G7="","",G7*I7) -> 199.56 | K7: 46317
A8: Computador | B8: Cartão Mercado Pago | C8: 46113 | D8: 3199.86 | E8: 18 | F8: 7 | G8: =IFERROR(D8/E8,"") -> 177.77 | H8: 6 | I8: =IF(E8="","",MAX(E8-H8,0)) -> 12 | J8: =IF(G8="","",G8*I8) -> 2133.24 | K8: 46303
A9: Moto | B9: Cartão Banco do Brasil | C9: 46296 | D9: 20196.6 | E9: 12 | F9: 11 | G9: =IFERROR(D9/E9,"") -> 1683.05 | H9: 11 | I9: =IF(E9="","",MAX(E9-H9,0)) -> 1 | J9: =IF(G9="","",G9*I9) -> 1683.05 | K9: 46307
G10: =IFERROR(D10/E10,"") | I10: =IF(E10="","",MAX(E10-H10,0)) | J10: =IF(G10="","",G10*I10)
G11: =IFERROR(D11/E11,"") | I11: =IF(E11="","",MAX(E11-H11,0)) | J11: =IF(G11="","",G11*I11)
G12: =IFERROR(D12/E12,"") | I12: =IF(E12="","",MAX(E12-H12,0)) | J12: =IF(G12="","",G12*I12)
G13: =IFERROR(D13/E13,"") | I13: =IF(E13="","",MAX(E13-H13,0)) | J13: =IF(G13="","",G13*I13)
G14: =IFERROR(D14/E14,"") | I14: =IF(E14="","",MAX(E14-H14,0)) | J14: =IF(G14="","",G14*I14)
G15: =IFERROR(D15/E15,"") | I15: =IF(E15="","",MAX(E15-H15,0)) | J15: =IF(G15="","",G15*I15)
G16: =IFERROR(D16/E16,"") | I16: =IF(E16="","",MAX(E16-H16,0)) | J16: =IF(G16="","",G16*I16)
G17: =IFERROR(D17/E17,"") | I17: =IF(E17="","",MAX(E17-H17,0)) | J17: =IF(G17="","",G17*I17)
G18: =IFERROR(D18/E18,"") | I18: =IF(E18="","",MAX(E18-H18,0)) | J18: =IF(G18="","",G18*I18)
G19: =IFERROR(D19/E19,"") | I19: =IF(E19="","",MAX(E19-H19,0)) | J19: =IF(G19="","",G19*I19)
G20: =IFERROR(D20/E20,"") | I20: =IF(E20="","",MAX(E20-H20,0)) | J20: =IF(G20="","",G20*I20)
G21: =IFERROR(D21/E21,"") | I21: =IF(E21="","",MAX(E21-H21,0)) | J21: =IF(G21="","",G21*I21)
... G103: =IFERROR(D103/E103,"") | I103: =IF(E103="","",MAX(E103-H103,0)) | J103: =IF(G103="","",G103*I103)

Sheet Dívidas
A1: Controle de dívidas
A3: Dívida | B3: Credor | C3: Saldo Inicial | D3: Saldo Atual | E3: Taxa mensal | F3: Parcela Mensal | G3: Vencimento | H3: Status | I3: Prioridade | J3: Previsão Quitação | K3: Observação
A4: Empréstimo Empresa | B4: Sicoob | C4: 15000 | D4: 6744.29 | E4: 0.052 | F4: 720.21 | G4: 5 | H4: Ativa | I4: Alta | J4: 46604 | K4: 19 parcelas
A5: Empréstimo Pedreiro | B5: Sicoob | C5: 6064.28 | D5: 3430.37 | E5: 0.0419 | F5: 877.97 | G5: 30 | H5: Ativa | I5: Média | J5: 46417 | K5: 7 parcelas

Sheet Metas
A1: Metas financeiras
A3: Meta | B3: Objetivo | C3: Valor Alvo | D3: Valor Atual | E3: Falta | F3: % Concluído | G3: Prazo | H3: Prioridade | I3: Aporte Mensal | J3: Observação
A4: Reserva de emergência | B4: 6 meses de despesas | C4: 30000 | D4: 0 | E4: =IF(C4="","",MAX(C4-D4,0)) -> 30000 | F4: =IFERROR(D4/C4,0) -> 0 | H4: Alta | I4: 1000
A5: Viagem | B5: Viagem de férias | C5: 7000 | D5: 0 | E5: =IF(C5="","",MAX(C5-D5,0)) -> 7000 | F5: =IFERROR(D5/C5,0) -> 0 | G5: 46334 | H5: Média | I5: 1000
A6: Compra Casa Vila Velha | B6: Quitar entrada de 70 k + 23 Par. | C6: 70000 | D6: 18000 | E6: =IF(C6="","",MAX(C6-D6,0)) -> 52000 | F6: =IFERROR(D6/C6,0) -> 0.25714286 | G6: 46832 | H6: Média | I6: 3000 | J6: Quitação em 20/03/2028
E7: =IF(C7="","",MAX(C7-D7,0)) | F7: =IFERROR(D7/C7,0) -> 0
E8: =IF(C8="","",MAX(C8-D8,0)) | F8: =IFERROR(D8/C8,0) -> 0
E9: =IF(C9="","",MAX(C9-D9,0)) | F9: =IFERROR(D9/C9,0) -> 0
E10: =IF(C10="","",MAX(C10-D10,0)) | F10: =IFERROR(D10/C10,0) -> 0
E11: =IF(C11="","",MAX(C11-D11,0)) | F11: =IFERROR(D11/C11,0) -> 0
E12: =IF(C12="","",MAX(C12-D12,0)) | F12: =IFERROR(D12/C12,0) -> 0
E13: =IF(C13="","",MAX(C13-D13,0)) | F13: =IFERROR(D13/C13,0) -> 0
E14: =IF(C14="","",MAX(C14-D14,0)) | F14: =IFERROR(D14/C14,0) -> 0
E15: =IF(C15="","",MAX(C15-D15,0)) | F15: =IFERROR(D15/C15,0) -> 0
E16: =IF(C16="","",MAX(C16-D16,0)) | F16: =IFERROR(D16/C16,0) -> 0
E17: =IF(C17="","",MAX(C17-D17,0)) | F17: =IFERROR(D17/C17,0) -> 0
E18: =IF(C18="","",MAX(C18-D18,0)) | F18: =IFERROR(D18/C18,0) -> 0
... E83: =IF(C83="","",MAX(C83-D83,0)) | F83: =IFERROR(D83/C83,0) -> 0

Sheet Planejamento Mensal
A1: Planejamento mensal — previsto x realizado
A3: Mês | B3: Receitas Prev. | C3: Receitas Real. | D3: Despesas Prev. | E3: Despesas Real. | F3: Saldo Prev. | G3: Saldo Real. | H3: Economia % | I3: Comprometimento % | J3: Observação
A4: 46235 | B4: =SUMIFS(Lançamentos!$H:$H,Lançamentos!$B:$B,A4,Lançamentos!$C:$C,"Receita") -> 17261.86 | C4: =SUMIFS(Lançamentos!$I:$I,Lançamentos!$B:$B,A4,Lançamentos!$C:$C,"Receita") -> 17632.86 | D4: =SUMIFS(Lançamentos!$H:$H,Lançamentos!$B:$B,A4,Lançamentos!$C:$C,"Despesa") -> 12557.44 | E4: =SUMIFS(Lançamentos!$I:$I,Lançamentos!$B:$B,A4,Lançamentos!$C:$C,"Despesa") -> 12565.1 | F4: =B4-D4 -> 4704.42 | G4: =C4-E4 -> 5067.76 | H4: =IFERROR(G4/C4,0) -> 0.28740431 | I4: =IFERROR(E4/C4,0) -> 0.71259569
A5: 46266 | B5: =SUMIFS(Lançamentos!$H:$H,Lançamentos!$B:$B,A5,Lançamentos!$C:$C,"Receita") -> 0 | C5: =SUMIFS(Lançamentos!$I:$I,Lançamentos!$B:$B,A5,Lançamentos!$C:$C,"Receita") -> 0 | D5: =SUMIFS(Lançamentos!$H:$H,Lançamentos!$B:$B,A5,Lançamentos!$C:$C,"Despesa") -> 0 | E5: =SUMIFS(Lançamentos!$I:$I,Lançamentos!$B:$B,A5,Lançamentos!$C:$C,"Despesa") -> 0 | F5: =B5-D5 -> 0 | G5: =C5-E5 -> 0 | H5: =IFERROR(G5/C5,0) -> 0 | I5: =IFERROR(E5/C5,0) -> 0
A6: 46296 | B6: =SUMIFS(Lançamentos!$H:$H,Lançamentos!$B:$B,A6,Lançamentos!$C:$C,"Receita") -> 0 | C6: =SUMIFS(Lançamentos!$I:$I,Lançamentos!$B:$B,A6,Lançamentos!$C:$C,"Receita") -> 0 | D6: =SUMIFS(Lançamentos!$H:$H,Lançamentos!$B:$B,A6,Lançamentos!$C:$C,"Despesa") -> 0 | E6: =SUMIFS(Lançamentos!$I:$I,Lançamentos!$B:$B,A6,Lançamentos!$C:$C,"Despesa") -> 0 | F6: =B6-D6 -> 0 | G6: =C6-E6 -> 0 | H6: =IFERROR(G6/C6,0) -> 0 | I6: =IFERROR(E6/C6,0) -> 0
A7: 46327 | B7: =SUMIFS(Lançamentos!$H:$H,Lançamentos!$B:$B,A7,Lançamentos!$C:$C,"Receita") -> 0 | C7: =SUMIFS(Lançamentos!$I:$I,Lançamentos!$B:$B,A7,Lançamentos!$C:$C,"Receita") -> 0 | D7: =SUMIFS(Lançamentos!$H:$H,Lançamentos!$B:$B,A7,Lançamentos!$C:$C,"Despesa") -> 0 | E7: =SUMIFS(Lançamentos!$I:$I,Lançamentos!$B:$B,A7,Lançamentos!$C:$C,"Despesa") -> 0 | F7: =B7-D7 -> 0 | G7: =C7-E7 -> 0 | H7: =IFERROR(G7/C7,0) -> 0 | I7: =IFERROR(E7/C7,0) -> 0
A8: 46357 | B8: =SUMIFS(Lançamentos!$H:$H,Lançamentos!$B:$B,A8,Lançamentos!$C:$C,"Receita") -> 0 | C8: =SUMIFS(Lançamentos!$I:$I,Lançamentos!$B:$B,A8,Lançamentos!$C:$C,"Receita") -> 0 | D8: =SUMIFS(Lançamentos!$H:$H,Lançamentos!$B:$B,A8,Lançamentos!$C:$C,"Despesa") -> 0 | E8: =SUMIFS(Lançamentos!$I:$I,Lançamentos!$B:$B,A8,Lançamentos!$C:$C,"Despesa") -> 0 | F8: =B8-D8 -> 0 | G8: =C8-E8 -> 0 | H8: =IFERROR(G8/C8,0) -> 0 | I8: =IFERROR(E8/C8,0) -> 0
A9: 46388 | B9: =SUMIFS(Lançamentos!$H:$H,Lançamentos!$B:$B,A9,Lançamentos!$C:$C,"Receita") -> 0 | C9: =SUMIFS(Lançamentos!$I:$I,Lançamentos!$B:$B,A9,Lançamentos!$C:$C,"Receita") -> 0 | D9: =SUMIFS(Lançamentos!$H:$H,Lançamentos!$B:$B,A9,Lançamentos!$C:$C,"Despesa") -> 0 | E9: =SUMIFS(Lançamentos!$I:$I,Lançamentos!$B:$B,A9,Lançamentos!$C:$C,"Despesa") -> 0 | F9: =B9-D9 -> 0 | G9: =C9-E9 -> 0 | H9: =IFERROR(G9/C9,0) -> 0 | I9: =IFERROR(E9/C9,0) -> 0
A10: 46419 | B10: =SUMIFS(Lançamentos!$H:$H,Lançamentos!$B:$B,A10,Lançamentos!$C:$C,"Receita") -> 0 | C10: =SUMIFS(Lançamentos!$I:$I,Lançamentos!$B:$B,A10,Lançamentos!$C:$C,"Receita") -> 0 | D10: =SUMIFS(Lançamentos!$H:$H,Lançamentos!$B:$B,A10,Lançamentos!$C:$C,"Despesa") -> 0 | E10: =SUMIFS(Lançamentos!$I:$I,Lançamentos!$B:$B,A10,Lançamentos!$C:$C,"Despesa") -> 0 | F10: =B10-D10 -> 0 | G10: =C10-E10 -> 0 | H10: =IFERROR(G10/C10,0) -> 0 | I10: =IFERROR(E10/C10,0) -> 0
A11: 46447 | B11: =SUMIFS(Lançamentos!$H:$H,Lançamentos!$B:$B,A11,Lançamentos!$C:$C,"Receita") -> 0 | C11: =SUMIFS(Lançamentos!$I:$I,Lançamentos!$B:$B,A11,Lançamentos!$C:$C,"Receita") -> 0 | D11: =SUMIFS(Lançamentos!$H:$H,Lançamentos!$B:$B,A11,Lançamentos!$C:$C,"Despesa") -> 0 | E11: =SUMIFS(Lançamentos!$I:$I,Lançamentos!$B:$B,A11,Lançamentos!$C:$C,"Despesa") -> 0 | F11: =B11-D11 -> 0 | G11: =C11-E11 -> 0 | H11: =IFERROR(G11/C11,0) -> 0 | I11: =IFERROR(E11/C11,0) -> 0
A12: 46478 | B12: =SUMIFS(Lançamentos!$H:$H,Lançamentos!$B:$B,A12,Lançamentos!$C:$C,"Receita") -> 0 | C12: =SUMIFS(Lançamentos!$I:$I,Lançamentos!$B:$B,A12,Lançamentos!$C:$C,"Receita") -> 0 | D12: =SUMIFS(Lançamentos!$H:$H,Lançamentos!$B:$B,A12,Lançamentos!$C:$C,"Despesa") -> 0 | E12: =SUMIFS(Lançamentos!$I:$I,Lançamentos!$B:$B,A12,Lançamentos!$C:$C,"Despesa") -> 0 | F12: =B12-D12 -> 0 | G12: =C12-E12 -> 0 | H12: =IFERROR(G12/C12,0) -> 0 | I12: =IFERROR(E12/C12,0) -> 0
A13: 46508 | B13: =SUMIFS(Lançamentos!$H:$H,Lançamentos!$B:$B,A13,Lançamentos!$C:$C,"Receita") -> 0 | C13: =SUMIFS(Lançamentos!$I:$I,Lançamentos!$B:$B,A13,Lançamentos!$C:$C,"Receita") -> 0 | D13: =SUMIFS(Lançamentos!$H:$H,Lançamentos!$B:$B,A13,Lançamentos!$C:$C,"Despesa") -> 0 | E13: =SUMIFS(Lançamentos!$I:$I,Lançamentos!$B:$B,A13,Lançamentos!$C:$C,"Despesa") -> 0 | F13: =B13-D13 -> 0 | G13: =C13-E13 -> 0 | H13: =IFERROR(G13/C13,0) -> 0 | I13: =IFERROR(E13/C13,0) -> 0
A14: 46539 | B14: =SUMIFS(Lançamentos!$H:$H,Lançamentos!$B:$B,A14,Lançamentos!$C:$C,"Receita") -> 0 | C14: =SUMIFS(Lançamentos!$I:$I,Lançamentos!$B:$B,A14,Lançamentos!$C:$C,"Receita") -> 0 | D14: =SUMIFS(Lançamentos!$H:$H,Lançamentos!$B:$B,A14,Lançamentos!$C:$C,"Despesa") -> 0 | E14: =SUMIFS(Lançamentos!$I:$I,Lançamentos!$B:$B,A14,Lançamentos!$C:$C,"Despesa") -> 0 | F14: =B14-D14 -> 0 | G14: =C14-E14 -> 0 | H14: =IFERROR(G14/C14,0) -> 0 | I14: =IFERROR(E14/C14,0) -> 0
A15: 46569 | B15: =SUMIFS(Lançamentos!$H:$H,Lançamentos!$B:$B,A15,Lançamentos!$C:$C,"Receita") -> 0 | C15: =SUMIFS(Lançamentos!$I:$I,Lançamentos!$B:$B,A15,Lançamentos!$C:$C,"Receita") -> 0 | D15: =SUMIFS(Lançamentos!$H:$H,Lançamentos!$B:$B,A15,Lançamentos!$C:$C,"Despesa") -> 0 | E15: =SUMIFS(Lançamentos!$I:$I,Lançamentos!$B:$B,A15,Lançamentos!$C:$C,"Despesa") -> 0 | F15: =B15-D15 -> 0 | G15: =C15-E15 -> 0 | H15: =IFERROR(G15/C15,0) -> 0 | I15: =IFERROR(E15/C15,0) -> 0

Sheet Planejamento Anual
A1: Planejamento anual
A3: Ano | B3: Receitas Prev. | C3: Receitas Real. | D3: Despesas Prev. | E3: Despesas Real. | F3: Saldo Prev. | G3: Saldo Real. | H3: Economia %
A4: 2026 | B4: =SUMIFS('Planejamento Mensal'!$B:$B,'Planejamento Mensal'!$A:$A,"*2026") -> 0 | C4: =SUMIFS('Planejamento Mensal'!$C:$C,'Planejamento Mensal'!$A:$A,"*2026") -> 0 | D4: =SUMIFS('Planejamento Mensal'!$D:$D,'Planejamento Mensal'!$A:$A,"*2026") -> 0 | E4: =SUMIFS('Planejamento Mensal'!$E:$E,'Planejamento Mensal'!$A:$A,"*2026") -> 0 | F4: =B4-D4 -> 0 | G4: =C4-E4 -> 0 | H4: =IFERROR(G4/C4,0) -> 0
A5: 2027 | B5: =SUMIFS('Planejamento Mensal'!$B:$B,'Planejamento Mensal'!$A:$A,"*2027") -> 0 | C5: =SUMIFS('Planejamento Mensal'!$C:$C,'Planejamento Mensal'!$A:$A,"*2027") -> 0 | D5: =SUMIFS('Planejamento Mensal'!$D:$D,'Planejamento Mensal'!$A:$A,"*2027") -> 0 | E5: =SUMIFS('Planejamento Mensal'!$E:$E,'Planejamento Mensal'!$A:$A,"*2027") -> 0 | F5: =B5-D5 -> 0 | G5: =C5-E5 -> 0 | H5: =IFERROR(G5/C5,0) -> 0
A6: 2028 | B6: =SUMIFS('Planejamento Mensal'!$B:$B,'Planejamento Mensal'!$A:$A,"*2028") -> 0 | C6: =SUMIFS('Planejamento Mensal'!$C:$C,'Planejamento Mensal'!$A:$A,"*2028") -> 0 | D6: =SUMIFS('Planejamento Mensal'!$D:$D,'Planejamento Mensal'!$A:$A,"*2028") -> 0 | E6: =SUMIFS('Planejamento Mensal'!$E:$E,'Planejamento Mensal'!$A:$A,"*2028") -> 0 | F6: =B6-D6 -> 0 | G6: =C6-E6 -> 0 | H6: =IFERROR(G6/C6,0) -> 0
A7: 2029 | B7: =SUMIFS('Planejamento Mensal'!$B:$B,'Planejamento Mensal'!$A:$A,"*2029") -> 0 | C7: =SUMIFS('Planejamento Mensal'!$C:$C,'Planejamento Mensal'!$A:$A,"*2029") -> 0 | D7: =SUMIFS('Planejamento Mensal'!$D:$D,'Planejamento Mensal'!$A:$A,"*2029") -> 0 | E7: =SUMIFS('Planejamento Mensal'!$E:$E,'Planejamento Mensal'!$A:$A,"*2029") -> 0 | F7: =B7-D7 -> 0 | G7: =C7-E7 -> 0 | H7: =IFERROR(G7/C7,0) -> 0
A8: 2030 | B8: =SUMIFS('Planejamento Mensal'!$B:$B,'Planejamento Mensal'!$A:$A,"*2030") -> 0 | C8: =SUMIFS('Planejamento Mensal'!$C:$C,'Planejamento Mensal'!$A:$A,"*2030") -> 0 | D8: =SUMIFS('Planejamento Mensal'!$D:$D,'Planejamento Mensal'!$A:$A,"*2030") -> 0 | E8: =SUMIFS('Planejamento Mensal'!$E:$E,'Planejamento Mensal'!$A:$A,"*2030") -> 0 | F8: =B8-D8 -> 0 | G8: =C8-E8 -> 0 | H8: =IFERROR(G8/C8,0) -> 0

Sheet Listas
A1: Listas de apoio
A2: Tipo | B2: Categoria | C2: Forma | D2: Status | E2: Prioridade
A3: Receita | B3: Moradia | C3: Dinheiro | D3: Previsto | E3: Alta
A4: Despesa | B4: Alimentação | C4: PIX | D4: Realizado | E4: Média
B5: Transporte | C5: Débito | D5: Pago | E5: Baixa
B6: Saúde | C6: Cartão | D6: Pendente
B7: Educação | C7: Transferência
B8: Lazer | C8: Boleto
B9: Assinaturas
B10: Empréstimo
B11: Padaria
B12: Devolução Dízimo
B13: Almoço
B14: Tarifa báncaria
B15: Barbeiro
B16: Salão
B17: Restaurante
B18: Impostos
B19: Compras
B20: Investimentos
... B25: Água
